kmerdb/CITATION.txt
kmerdb/__init__.py
kmerdb/__main__.py
kmerdb/config.py
kmerdb/distance.c
kmerdb/distance.cpython-310-x86_64-linux-gnu.so
kmerdb/distance.pyx
kmerdb/fileutil.py
kmerdb/index.py
kmerdb/kmer.py
kmerdb/parse.py
kmerdb/probability.py
kmerdb/python_distances.py
kmerdb/seqparser.py
kmerdb/util.py
kmerdb-0.7.4.dist-info/LICENSE.txt
kmerdb-0.7.4.dist-info/METADATA
kmerdb-0.7.4.dist-info/WHEEL
kmerdb-0.7.4.dist-info/entry_points.txt
kmerdb-0.7.4.dist-info/top_level.txt
kmerdb-0.7.4.dist-info/RECORD
