Metadata-Version: 2.1
Name: kmerdb
Version: 0.7.4
Summary: Yet another kmer library for Python
Home-page: https://github.com/MatthewRalston/kmerdb
Download-URL: https://github.com/MatthewRalston/kmerdb/archive/v0.7.0.tar.gz
Author: Matthew Ralston
Author-email: "Matt Ralston <mralston.development@gmail.com>" <mralston.development@gmail.com>
License: 
Project-URL: Homepage, https://matthewralston.github.io/kmerdb
Project-URL: QuickStart, https://matthewralston.github.io/kmerdb/quickstart.html
Project-URL: Install, https://matthewralston.github.io/kmerdb/installation.html
Project-URL: ForAcademics, https://matthewralston.github.io/kmerdb/academics.html
Project-URL: Github, https://github.com/MatthewRalston/kmerdb
Project-URL: Issues, https://github.com/MatthewRalston/kmerdb/issues
Keywords: bioinformatics,fastq,fasta,k-mer,kmer,k-merdb,kmerdb,kdb
Classifier: Development Status :: 1 - Planning
Classifier: Intended Audience :: Developers
Classifier: Intended Audience :: Science/Research
Classifier: License :: OSI Approved :: Apache Software License
Classifier: Operating System :: OS Independent
Classifier: Programming Language :: Python
Classifier: Programming Language :: Python :: 3
Classifier: Programming Language :: Python :: 3.6
Classifier: Programming Language :: Python :: 3.7
Classifier: Programming Language :: Python :: 3.8
Classifier: Programming Language :: Python :: 3.9
Classifier: Programming Language :: Python :: 3.10
Classifier: Topic :: Scientific/Engineering
Classifier: Topic :: Scientific/Engineering :: Bio-Informatics
Classifier: Topic :: Software Development :: Libraries :: Python Modules
Requires-Python: >=3.8.0
License-File: LICENSE.txt
Requires-Dist: biopython (>=1.79)
Requires-Dist: cython (>=0.29.26)
Requires-Dist: distlib (>=0.3.4)
Requires-Dist: matplotlib (>=3.6.2)
Requires-Dist: numpy (>=1.22.0)
Requires-Dist: pandas (>=1.3.5)
Requires-Dist: scipy (>=1.9.3)
Requires-Dist: sklearn (>=0.0.post1)
Requires-Dist: rpy2 (>=3.5.6)
Requires-Dist: PyYAML (>=6.0)
Requires-Dist: jsonschema (>=4.17.3)
Requires-Dist: psutil (>=5.9.4)
Provides-Extra: dev
Requires-Dist: auditwheel (>=5.1.2) ; extra == 'dev'
Requires-Dist: build (>=0.9.0) ; extra == 'dev'
Requires-Dist: coverage (>=4.5.4) ; extra == 'dev'
Requires-Dist: expects (>=0.9.0) ; extra == 'dev'
Requires-Dist: docutils (>=0.17) ; extra == 'dev'
Requires-Dist: sphinx (>=4.3.2) ; extra == 'dev'
Requires-Dist: sphinx-autodoc ; extra == 'dev'
Requires-Dist: sphinx-rtd-theme (>=1.0.0) ; extra == 'dev'
Requires-Dist: pytest (>=5.3.5) ; extra == 'dev'
Requires-Dist: twine (==4.0.1) ; extra == 'dev'
